src/shopify_py_mcp/__init__.py
src/shopify_py_mcp/server.py
orange_shopify_py_mcp-0.1.0.dist-info/METADATA
orange_shopify_py_mcp-0.1.0.dist-info/WHEEL
orange_shopify_py_mcp-0.1.0.dist-info/entry_points.txt
orange_shopify_py_mcp-0.1.0.dist-info/licenses/LICENSE
orange_shopify_py_mcp-0.1.0.dist-info/RECORD
