Metadata-Version: 2.4
Name: orange-shopify-py-mcp
Version: 0.1.0
Summary: A MCP server project
Author-email: masashi kishimoto <drehbleistift@gmail.com>
License-File: LICENSE
Requires-Python: >=3.11.6
Requires-Dist: mcp>=1.3.0
Requires-Dist: shopifyapi>=1.0.0
